odoo10_addon_delivery_carrier_file_tnt-10.0.1.0.1-py3.8-nspkg.pth
odoo/addons/delivery_carrier_file_tnt/README.rst
odoo/addons/delivery_carrier_file_tnt/__init__.py
odoo/addons/delivery_carrier_file_tnt/__manifest__.py
odoo/addons/delivery_carrier_file_tnt/generator/__init__.py
odoo/addons/delivery_carrier_file_tnt/generator/tnt_generator.py
odoo/addons/delivery_carrier_file_tnt/i18n/de.po
odoo/addons/delivery_carrier_file_tnt/i18n/delivery_carrier_file_tnt.pot
odoo/addons/delivery_carrier_file_tnt/i18n/fr.po
odoo/addons/delivery_carrier_file_tnt/models/__init__.py
odoo/addons/delivery_carrier_file_tnt/models/delivery_carrier_file.py
odoo/addons/delivery_carrier_file_tnt/static/description/icon.png
odoo/addons/delivery_carrier_file_tnt/views/delivery_carrier_file.xml
odoo10_addon_delivery_carrier_file_tnt-10.0.1.0.1.dist-info/METADATA
odoo10_addon_delivery_carrier_file_tnt-10.0.1.0.1.dist-info/WHEEL
odoo10_addon_delivery_carrier_file_tnt-10.0.1.0.1.dist-info/namespace_packages.txt
odoo10_addon_delivery_carrier_file_tnt-10.0.1.0.1.dist-info/top_level.txt
odoo10_addon_delivery_carrier_file_tnt-10.0.1.0.1.dist-info/RECORD
